xn_twist_python_sdk/__init__.py
xn_twist_python_sdk/utility.py
xn_twist_python_sdk/xn_twist_python.py
xn_twist_python_sdk-5.0.0.dist-info/METADATA
xn_twist_python_sdk-5.0.0.dist-info/RECORD
xn_twist_python_sdk-5.0.0.dist-info/WHEEL
xn_twist_python_sdk-5.0.0.dist-info/top_level.txt
xn_twist_python_sdk-5.0.0.dist-info/zip-safe
