Metadata-Version: 2.1
Name: xn-twist-python-sdk
Version: 5.0.0
Summary: Python SDK for XN-Twist's API
Home-page: https://github.com/xn-twist/xn-twist-python-sdk
Author: Floyd Hightower
Author-email: UNKNOWN
License: 
Requires-Dist: Requests
